{
  "dataset": {
    "docmeta": {
      "identifier": "FIRM_2021_jua_ENTER_001.xml",
      "doi": "work_2012-11_2012-11-28_ain_0001",
      "subject": "FIRM_ENTER Yritystietovarasto: yritykset 2021",
      "contentdescription": "Yritysrekisterin yritystason aineisto kattaa liikeyritysten ja yksityisten voittoa tavoittelemattomien yhteisöjen vuosittaiset yritystason tilastotiedostot. Aineisto sisältää perustiedot yritysten toimialasta, sijainnista, omistuksesta, liikevaihdosta, henkilöstömäärästä ja palkoista. \n\nTilaston perusaineistona ovat Tilastokeskuksen yritys- ja toimipaikkarekisteriin kuuluvat liiketoimintaa harjoittavat yritykset ja toimipaikat. Se sisältää kaikki yritykset, yhteisöt ja yksityiset elinkeinonharjoittajat, jotka ovat liiketoiminnasta arvonlisäverovelvollisia tai toimivat työnantajina. Julkisyhteisöt ovat saatavissa erillisestä julkisyhteisöjen rekisteristä.\n\nTilastoon tulevat yritykset, jotka ovat toimineet yli puoli vuotta tilastovuonna ja jotka ovat työllistäneet enemmän kuin puoli henkilöä tai tase ylittää 170 000 euroa tai nettoinvestoinnit ylittää 50 000 euroa tai joiden liikevaihto on ylittänyt vuosittain määritellyn tilastorajan (12 273 euroa vuonna 2021).Toimialalta A (Maatalous, metsätalous ja kalatalous) maatiloista ovat mukana tilat, joiden maataloustulos on tilastovuonna ylittänyt liikevaihdon tilastorajan. Maatilataloudesta saadaan kattavasti vain henkilöstötiedot. Toimialalta 02 mukana ovat ne yksiköt, joiden tuotot metsätaloudesta ylittävät tilastorajan. Rahoitus- ja vakuutustoiminnasta (TOL K) julkaistaan vuodesta 2021 alkaen liikevaihto, jalostusarvo, yritysten lukumäärät ja henkilöstömäärätiedot.\n\nMuutos tv. 2018 syritysid: Yritysyksikkö vastaa pienintä oikeudellisten yksiköiden ryhmää, joka muodostaa päätöksenteossaan itsenäisen tuotantoyksikön. Saman syritysid alla voi olla eri syrtun.\n\nMuutos tv. 2021\nYritysten rakennetilastoissa tehdään syksyllä 2022 uudistuksia, jotka aiheuttavat aikasarjakatkoksen vuosien 2020–2021 välille.\nTilastovuodesta 2021 alkaen tilaston henkilöstömäärä- ja palkkasummatiedot on laskettu uudella menetelmällä uutta tulorekisterin aineistoa käyttäen. Henkilöstömäärät ja palkkasummat eivät uudistuksen vuoksi ole täysin vertailukelpoisia aiempiin vuosiin verrattuna. Uudistus laskee henkilöstömääriä noin 136 000 henkilöllä (9,0 %), kun taas palkkasumma kasvaa noin 66 miljoonalla eurolla (0,1 %) vuoden 2020 tiedoilla laskettuna.\n\nTilastoon otetaan tilastovuodesta 2021 alkaen mukaan Verohallinnon arvioverottamien yritysten estimoidut tuloslaskelmatiedot. Aiemmin näiden yritysten tuloslaskelmat eivät ole olleet tilastossa mukana. Muutos lisää tilastossa olevan liikevaihdon määrää yhteensä noin 700 miljoonalla eurolla vuoden 2020 tiedoilla laskettuna.\n\nTilastosta on tilastovuodesta 2021 alkaen poistettu suurimmilta yksiköiltä ulkomailla sijaitsevien sivuliikkeiden tiedot. Muutos aiheuttaa aikasarjakatkoksen osalle toimialoista aiempiin vuosiin verrattuna.\n\nTiedot kerätään pääasiassa kahdesta lähteestä: verohallinnon rekistereistä ja yritysrekisterin tiedusteluista. \nVerohallituksen eri rekistereistä saadaan yrityksen aloitus- ja lopetustiedot, kotikunta, alustava toimialatieto uusille yrityksille, liikevaihto ja palkat.\nYritysrekisterin tiedusteluilla kerätään vuosittain kaikkien monitoimipaikkaisten ja vähintään 20 henkilöä työllistävien yksitoimipaikkaisten yritysten tiedot. Alle 20 henkilöä työllistävistä yrityksistä tiedustellaan yksiköt, joilla tiedot hallinnollisten rekistereiden, kaupallisten aineistojen tai Tilastokeskuksen muiden tiedustelujen perusteella ovat muuttuneet. Perustetut yritykset sisällytetään yleensä tiedusteluun melko pian toiminnan aloittamisen jälkeen. Omista tiedusteluista saadaan muun muassa henkilöstön määrä, liikevaihto, toimiala ja sijaintikunta. Tiedusteluihin sisältymättömien yritysten henkilöstön määrä estimoidaan palkkatietojen perusteella. Palkansaajien määrä estimoidaan Verohallinnon verotusaineiston palkkatietojen perusteella. Yrittäjät estimoidaan kaikille yrittäjäeläkettä ja palkkaa maksaneille. Estimointimalli perustuu yritysten maksamiin palkkoihin, toimialaan sekä sen työntekijöiden taustatietoihin. Täydentävänä tietona käytetään myös liikevaihdon kuukausikuvaajien tietoja yritysten maksamista palkoista.\n\nYritystilastojen tilastoinnin muutosten vuoksi vuosien 2013-  tiedot eivät ole vertailukelpoisia edeltäviin tilastoihin nähden. Tietojärjestelmän uudistus on parantunut yritystilastojen yhtenäisyyttä. Merkittävimmät muutokset liittyvät toimialaluokituksen, yritystietojen (mm. liikevaihto- ja henkilöstötieto) ja yritysjärjestelyjen käsittelyn yhtenäistämiseen sekä päättelysääntöihin, jonka perusteella tilastoitava yritys- tai toimipaikkajoukko muodostetaan. Aiemmin yritysrekisterin vuositilastoissa ei ollut tase-ehtoa yrityksen vuositilastoon kuulumisen ratkaisemiseksi, eikä kohdejoukkoon ole kuuluneet kunnalliset liikelaitokset. Alkutuotannon toimialojen osalta tilastossa ovat tilastovuodesta 2013 alkaen mukana alkutuotannosta arvonlisäverovelvolliset, kun myynnit ylittävät tilastointirajan.\n\nTilastoraja, liikevaihto\n2013, 10 846\n2014, 11 016\n2015, 11 196\n2016, 11 296\n2017, 11 376 \n2018, 11 598\n2019, 11 810 \n2020, 11 968\n2021, 12 273\n\nLisätietoja Tilastokeskuksen tutkijapalveluista: tutkijapalvelut@tilastokeskus.fi.",
      "coveragetemporal": "2020-01-01 - 2021-12-31",
      "published_day": "2023-02-10",
      "variable_count": "41",
      "orgname": "Tilastokeskus",
      "coveragepopulation": "Yritykset. Yksilöintitunnuksena liiketunnus.",
      "resourcerelation_1": "Yritys- ja toimipaikkarekisteri",
      "resourcerelation_2": "<a href= \"http://www.stat.fi/til/yrti/index.html\">Yritysten rakenne- ja tilinpäätöstilasto</a> <a href= \"http://www.stat.fi/meta/rekisteriselosteet/tutka_rekisteriseloste_yritysrekisterin_yritykset.html\">Yritysrekisterin yritykset</a> ",
      "keywords": "yritykset,yritysrekisteri",
      "line_count": "370252",
      "everything_else": "asdf"
    },
    "statmeta": "metaa..."
  }
}
