{
  "dataset": {
    "docmeta": {
      "identifier": "EDUC_20002004_jua_harekamk_001.xml",
      "doi": "khak_2024-08_2024-08-09_ain_0001",
      "subject": "EDUC_HAREK Ammattikorkeakoulujen hakurekisteritiedot 2000-2004",
      "contentdescription": "Tämä aineisto on osa laajempaa EDUC-HAREK -moduulia korkeakoulujen hakurekisteritiedoista 1992-2022. Tämä aineisto sisältää ammattikorkeakoulujen kalenterivuonna alkaneeseen koulutukseen hakeneiden hakurekisterin tiedot 2000-2004, siltä osin kun tiedot on toimitettu Tilastokeskukseen tilastointia varten. Kokonaisuus sisältää tietoja muun muassa hakemuksesta, hakijasta ja hakukohteesta. \n\n<h3>Tietolähde</h3>\nAineisto korkeakoulujen hakijoista ja opiskelijavalinnoista perustuu Opetushallituksen ylläpitämiin hakija- ja opinto-oikeusrekisteritietoihin. Tilastokeskukseen toimitetun tiedon määrä vaihtelee aikaperiodeittain, ja tiedostoihin on lisätty tietoja Tilastokeskuksessa tilastotuotannossa. Tiedostoista on salattu henkilön tunnistetiedot. Lisäksi tiedostoista on suojattu mm. oppilaitosten tunnistetiedot.\n \n<h3>Huomioitavaa</h3>\nTiedot on linkitettävissä muiden henkilövalmisaineistomoduulien kanssa suojatun henkilönumeron avulla. Huomaathan, että hakijoille, joilla ei ole suomalaista henkilötunnusta, ei olla voitu muodostaa suojattua henkilönumeroa (shnro). Tällöin heille on pyritty luomaan korvaava shetu, joka toimii hakijan tunnisteena vain kunkin vuosiaineiston sisällä. Tämän avulla voidaan pyrkiä tunnistamaan usealla rivillä esiintyvät saman hakijan tiedot. Muuttuja (shetu) ei yhdisty aineistojen välillä, ja muuttujassa esiintyy myös vaillinaisista tiedoista johtuvia virheitä. Huomaathan, että osalle hakijoista ei olla pystytty muodostamaan shnro- eikä shetu-muuttujaa, ja henkilönumerottomien hakijoiden määrä vaihtelee huomattavasti eri vuosina.\n \nModuulin muuttujasisällöissä on suuria eroja yli ajan. Tämä vuosilta 2000-2004 koostettu kokonaisuus ammattikorkeakoulujen hakutiedoista on ryhmitelty sen mukaisesti, että vuosilta on ollut saatavilla samankaltainen muuttujasisältö, mutta myös tämän kokonaisuuden sisällä muuttujasisällössä on vuosittaisia eroavaisuuksia. Kaikki ohessa listatut muuttujat eivät ole saatavilla koko aikaväliltä, ja muuttujien käytössä tuleekin ottaa huomioon tietojen rajoittuneisuus ja mahdolliset puutteet. <b>Huomaathan, että oppiaine- ja arvosanatietoja (edellisten opintojen tiedot, joiden perusteella hakija on hakemassa korkeakouluun) on saatavilla ammattikorkeakouluhakujen osalta vuosilta 1996-1999 hakukorttiperusteisesti, jonka lisäksi aineistovuosille 2000-2005 näitä tietoja on yhdistetty jälkikäteen saatavilta osin ammattikorkeakoulujen yhteishakuun osallistuneilta.</b> Erityisesti arvosana- ja oppiainemuuttujissa voi ilmetä puutteita, ja niiden oikeellisuutta ei ole pystytty tarkistamaan. Arvosanatietojen käytössä tulee ottaa huomioon tietojen rajallisuus varsinkin, sillä tietoja on yhdistetty jälkikäteen saatavilta osin.\n \nHakurekisteri on saatavilla yhdistettynä korkeakouluhakurekisterinä vuodesta 2015 eteenpäin ja erikseen yliopistoille ja ammattikorkeakouluille ennen vuotta 2015, joista yliopistojen osalta hakutiedostot alkavat vuodesta 1992 ja ammattikorkeakoulujen osalta vuodesta 1996. Osa ammattikorkeakoulujen hakutiedostoista eri vuosilta ovat samankaltaisia kuin toisen asteen yhteishakurekisterin tiedot. EDUC-HAREK -moduuli on ryhmitelty seuraaviin kokonaisuuksiin, joilla on kullakin oma Taika-kuvauksensa:\n* ammattikorkeakoulujen hakurekisteritiedot 1996-1999\n* ammattikorkeakoulujen hakurekisteritiedot 2000-2004\n* ammattikorkeakoulujen hakurekisteritiedot 2005-2014\n* yliopistojen hakurekisteritiedot 1992-1998\n* yliopistojen hakurekisteritiedot 1999-2003\n* yliopistojen hakurekisteritiedot 2004-2009\n* yliopistojen hakurekisteritiedot 2010-2014\n* yhdistetyt korkeakoulujen hakurekisteritiedot 2015–\nKunkin osakokonaisuuden kuvauksesta löytyy tarkemmat tiedot tietosisällöstä.\nKaikkien tietojen oikeellisuudesta ei olla voitu varmistua. Huomaathan, että muuttujien kuvauksissa on voitu dokumentoida kokonaisuuden aikavälillä muuttujan sisällössä mahdollisesti tapahtuneita muutoksia ja muuttujan käytössä huomioon otettavia seikkoja. \n\nEDUC-HAREK -moduulin aineisto koostuu erillisistä vuositiedostoista:\n- EDUC_HAREK_amkhaku_VVVV, jossa VVVV = 1996, ..., 2014.\n- EDUC_HAREK_yohaku_VVVV, jossa VVVV = 1992, ..., 2014.\n- EDUC_HAREK_kkhaku_VVVV, jossa VVVV = 2015, ..., 2023.\nTiedostot sisältävät nimiensä mukaisesti ammattikorkeakoulujen hakurekisteritietoja, yliopistojen hakurekisteritietoja, ja yhdistettyjä korkeakoulujen hakurekisteritietoja kukin niiltä vuosilta, joilta aineistoa on saatavilla.\n\nHakurekisteristä on erikseen saatavilla arkaluonteisia ja karkeistamattomia muuttujia, joihin annetaan käyttöoikeus vain, jos niihin on tutkimuksellisesta syystä erityinen tarve. Tällaisia ovat esimerkiksi karkeistamaton äidinkielitieto tai karkeistamaton kansalaisuustieto. Niillä moduulin karkeistetuilla tiedoilla, joista on karkeistamaton tieto saatavissa esimerkiksi Tilastokeskuksen tietovarannoista, on loppulyhenteenä _k.\n\nLisätietoja Tilastokeskuksen tutkijapalveluista: tutkijapalvelut@stat.fi\n",
      "coveragetemporal": "2000-01-01 - 2004-12-31",
      "published_day": "2025-03-07",
      "variable_count": "200",
      "orgname": "Tilastokeskus",
      "coveragepopulation": "korkeakouluhakijat",
      "resourcerelation_1": "Aineisto opiskelijavalinnoista perustuu Opetushallituksen ylläpitämään opiskelijavalintarekisteriin (sis. yliopistojen hakija- ja opinto-oikeusrekisterin, ammattikorkeakoulujen yhteishakurekisterin, ja korkeakoulujen hakurekisterin tiedot ajankohdan mukaisesti), jonka OPH toimittaa Tilastokeskukselle vuosittain.\nTiedoissa hakeneista ja hyväksytyistä korkeakouluihin hyväksytyillä tarkoitetaan lähtökohtaisesti kaikkia kunakin hakuvuonna 15.9. mennessä hyväksymiskirjeen saaneita.",
      "resourcerelation_2": "<a href= \"https://stat.fi/tilasto/khak#contacts\">Tilastotieto: Koulutukseen hakeutuminen</a> ",
      "keywords": "koulutus,oppilaitokset",
      "line_count": null,
      "everything_else": "asdf"
    },
    "statmeta": "metaa..."
  }
}
