{
  "dataset": {
    "docmeta": {
      "identifier": "YA231_2014_jua_innovaatiot_002.xml",
      "doi": "inn_2012-12_2012-12-03_ain_0001",
      "subject": "FIRM_RDINNO Innovaatiotutkimus 2014 (YA231)",
      "contentdescription": "Innovaatiotutkimus 2014 kuvaa yritysten harjoittaman innovaatiotoiminnan ja eri tyyppisten innovaatioiden käyttöönoton yleisyyttä vuosina 2012 - 2014. \n\nJoka toinen vuosi toteutettava yritysten innovaatiotoiminta -tutkimus on osa Eurostatin koordinoimaa, kaikissa EU:n jäsenmaissa toteutettavaa yhteishanketta Community Innovation Survey (CIS). Innovaatiotutkimuksen keskeisenä tavoitteena on selvittää yritysten harjoittaman innovaatiotoiminnan yleisyys sekä kartoittaa innovaatiotoimintaan liittyviä piirteitä ja toimenpiteitä. Tutkimuksessa käytetään EU-harmonisoitua tiedonkeruulomaketta sekä yhtenäisiä rajauksia ja menetelmiä. Tutkimuksen keskeiset käsitteet perustuvat OECD:n ja Eurostatin määritelmiin (Oslo Manual, Guidelines for collecting and interpreting innovation data, 3rd edition, OECD 2005).\n\nInnovaatiotoiminta ja innovaatiot ovat taloudellisen kasvun ja kehityksen, kilpailukyvyn ja hyvinvoinnin edellytyksiä. Tutkimus- ja kehittämistoiminta (t&k) on keskeinen innovaatiotoiminnan osatekijä, mutta kokonaisuudessaan innovaatiotoiminta on huomattavasti tutkimus- ja kehittämistoimintaa laajempi käsite. Innovaatiotoiminta sisältää lukuisia tutkimus- ja kehittämistoimintaan kuulumattomia toimia; innovaatioindikaattorit ja -tilastot kuvaavat yritysten kehittämisprosesseja alusta loppuun, aina ideoiden tietolähteistä käyttöönotettujen innovaatioiden yleisyyteen.\n\nInnovaatio on yrityksen markkinoille tuoma uusi tai olennaisesti parannettu tuote (tavara tai palvelu), yrityksen käyttöön ottama uusi tai olennaisesti parannettu prosessi, yrityksen käyttöön ottama uusi markkinointimenetelmä tai yrityksen käyttöön ottama uusi organisatorinen menetelmä liiketoimintakäytännöissä, työorganisaatiossa tai ulkoisissa suhteissa. Innovaation (tuotteen, prosessin, markkinointimenetelmän tai organisatorisen menetelmän) on oltava uusi kyseisen yrityksen kannalta.\n\nInnovaatiotoimintatilasto sisältää tietoja tuote- ja prosessi-innovaatioihin liittyvän innovaatiotoiminnan yleisyydestä ja luonteesta yrityksissä sekä tietoja mm. markkinointi- ja organisaatioinnovaatioiden käyttöönoton yleisyydestä. Innovaatiotoiminnan laajuutta ja luonnetta kuvataan muun muassa yritysten suuruusluokan ja toimialan mukaan. Tutkimuksen kohteena ovat vähintään kymmenen henkilöä työllistävät yritykset teollisuudessa (ml. kaivostoiminta ja louhinta sekä sähkö-, kaasu- ja lämpöhuolto ja vesi- ja jätehuolto) sekä eräillä palvelualoilla.\n\nTutkimus sisältää seuraavat tiedot jokaiselta tiedonkeruukierrokselta:\n-\ttuoteinnovaatioiden markkinoille tuonti \n-\tprosessi-innovaatioidenkäyttöönotto\n-\ttuote- ja prosessi-innovaatioiden kehittämiseen liittyvät hankkeet \n-\ttuoteinnovaatioiden uutuus; markkinoiden kannalta ja vain yrityksen kannalta uudet tuotteet \n-\ttuoteinnovaatioista saadun liikevaihdon osuus kokonaisliikevaihdosta \n-\ttuote- ja prosessi-innovaatioiden kehittäjä \n-\tinnovaatiotoimintaan liittyvä yhteistyö (tuote- ja prosessi-innovaatioihin liittyvä toiminta)\n\nLisäksi innovaatiotutkimuksessa 2014 tiedustellaan seuraavia tietoja:\n-\tyrityksen maantieteelliset markkinat\n-\tinnovaatiotoiminnan julkinen rahoitustuki (tuote- ja prosessi-innovaatioihin liittyvä toiminta)\n-\tmarkkinointi-innovaatioiden käyttöönotto\n\nEU-kysymysten lisäksi tutkimus kattaa ajoittain myös kansallisia kysymyksiä ajankohtaisista aiheista, kuten:\n-\tbig datan ja julkisen sektorin avoimen datan käyttö (tuote- ja prosessi-innovaatioihin liittyvä toiminta) \n-\tdigitalisaatio\n-\tkäyttäjälähtöisyys innovaatiotoiminnassa\n\nTiedot kerätään yrityksiltä (kokonaistutkimus vähintään 250 henkilöä työllistävistä yrityksistä, otantatutkimus 10 - 249 henkilöä työllistävistä yrityksistä, otantamenetelmänä ositettu yksinkertainen satunnaisotanta). Pääasiallisin tietojen toimitustapa on sähköinen lomake. Kysely koskee sekä innovaatiotoimintaa harjoittaneita yrityksiä että yrityksiä, joilla ei ollut innovaatiotoimintaa vuosina 2012 - 2014.\n\nTilastokeskus on tehnyt innovaatiotutkimuksia 1990-luvulta lähtien, mutta kaikkien tutkimusten tiedot eivät ole vertailukelpoisia keskenään. Tämä johtuu käsitteisiin ja näiden määritelmiin tehdyistä muutoksista, kysymyksen asetteluihin tehdyistä muutoksista sekä mm. muutoksista luokituksissa.\n\nLisätietoja Tilastokeskuksen tutkijapalveluista: tutkijapalvelut@tilastokeskus.fi.",
      "coveragetemporal": "2012-01-01 - 2014-12-31",
      "published_day": "2019-03-27",
      "variable_count": "178",
      "orgname": "Tilastokeskus",
      "coveragepopulation": "Vähintään 10 henkilöä työllistävät yritykset teollisuudessa sekä eräillä palvelualoilla",
      "resourcerelation_1": "Tilastokeskuksen innovaatiotutkimus",
      "resourcerelation_2": "<a href= \"http://tilastokeskus.fi/til/inn/index.html\">Innovaatiotoiminta</a> <a href= \"http://www.stat.fi/meta/rekisteriselosteet/tutka_rekisteriseloste_innovaatiotoiminta.html\">Innovaatiotoiminta</a> ",
      "keywords": "innovaatiot,innovaatiotoiminta,tuotekehitys,tutkimus- ja kehittämistoiminta,yritykset",
      "line_count": "2414",
      "everything_else": "asdf"
    },
    "statmeta": "metaa..."
  }
}
