{
  "dataset": {
    "docmeta": {
      "identifier": "KELA_20172018_jua_perustulojaksot_001.xml",
      "doi": "_2021-01_2021-01-25_ain_0001",
      "subject": "KELA_perustulorekisteri, Perustulojaksot",
      "contentdescription": "Kelan perustulokokeilurekisteri on suojattu tutkimuskäyttöön. Tutkija hakee aineistolle käyttölupaa Kelasta.\n\nAineisto sisältää neljä taulua: \n \n1. Perustulokokeilun kohdejoukko \n2. Perustulojaksot \n3. Perustulomaksut  \n4. Poiskuittaukset etuuksista  \n\nTaulut 1 ja 2 muodostavat Perustulokokeilusta annetun lain (1528/2016) 18 §:n mukaisen perustulorekisterin. Taulut 3 ja 4 on muodostettu Kelassa helpottamaan varsinaisen perustulorekisterin käyttöä tutkimuksessa. Taulut muuttujineen on kuvattu tarkemmin erikseen. Taulut voi yhdistää henkilötasolla muuttujaa SHNRO avaimena käyttäen. \n\nTaulu sisältää perustulon ratkaisuihin liittyvät tiedot. Kukin ratkaisu kohdistuu tiettyyn ajanjaksoon. Alkuperäisen, koko perustulokokeilun ajan kattavan myöntöpäätöksen lisäksi ratkaisu voi olla esimerkiksi perustulon lakkautus tietyltä ajanjaksolta. Lisätietoa Perustulokokeilusta: https://www.finlex.fi/fi/laki/alkup/2016/20161528\n",
      "coveragetemporal": "2017-01-01 - 2018-12-31",
      "published_day": "2021-02-02",
      "variable_count": "8",
      "orgname": "Tilastokeskus",
      "coveragepopulation": "Perustulokokeilun kohdejoukko",
      "resourcerelation_1": "Kansaneläkelaitoksen perustulokokeilurekisteri",
      "resourcerelation_2": null,
      "keywords": null,
      "line_count": null,
      "everything_else": "asdf"
    },
    "statmeta": "metaa..."
  }
}
